bintensors-0.2.0.dist-info/METADATA
bintensors-0.2.0.dist-info/WHEEL
bintensors/torch.py
bintensors/flax.py
bintensors/__init__.py
bintensors/mlx.py
bintensors/numpy.py
bintensors/__init__.pyi
bintensors/_bintensors_rs.abi3.so
bintensors-0.2.0.dist-info/RECORD
