Metadata-Version: 2.4
Name: bintensors
Version: 0.2.0
Classifier: Programming Language :: Rust
Classifier: Programming Language :: Python :: Implementation :: CPython
Classifier: Programming Language :: Python :: Implementation :: PyPy
Classifier: Development Status :: 4 - Beta
Classifier: Intended Audience :: Developers
Classifier: Intended Audience :: Education
Classifier: Intended Audience :: Science/Research
Classifier: Operating System :: OS Independent
Classifier: Programming Language :: Python :: 3
Classifier: Programming Language :: Python :: 3.7
Classifier: Programming Language :: Python :: 3.8
Classifier: Programming Language :: Python :: 3.9
Classifier: Programming Language :: Python :: 3.10
Classifier: Topic :: Scientific/Engineering :: Artificial Intelligence
Classifier: Typing :: Typed
Requires-Dist: numpy>=1.21.6 ; extra == 'numpy'
Requires-Dist: bintensors[numpy] ; extra == 'torch'
Requires-Dist: torch>=1.10 ; extra == 'torch'
Requires-Dist: bintensors[numpy] ; extra == 'jax'
Requires-Dist: flax>=0.6.3 ; extra == 'jax'
Requires-Dist: jax>=0.3.25 ; extra == 'jax'
Requires-Dist: jaxlib>=0.3.25 ; extra == 'jax'
Requires-Dist: mlx>=0.0.9 ; extra == 'mlx'
Requires-Dist: black==22.3 ; extra == 'quality'
Requires-Dist: click==8.0.4 ; extra == 'quality'
Requires-Dist: isort>=5.5.4 ; extra == 'quality'
Requires-Dist: flake8>=3.8.3 ; extra == 'quality'
Requires-Dist: bintensors[numpy] ; extra == 'testing'
Requires-Dist: bintensors[torch] ; extra == 'testing'
Requires-Dist: bintensors[mlx] ; extra == 'testing'
Requires-Dist: bintensors[jax] ; extra == 'testing'
Requires-Dist: setuptools-rust>=1.5.2 ; extra == 'testing'
Requires-Dist: pytest>=7.2.0 ; extra == 'testing'
Requires-Dist: pytest-benchmark>=4.0.0 ; extra == 'testing'
Requires-Dist: hypothesis>=6.70.2 ; extra == 'testing'
Requires-Dist: bintensors[torch] ; extra == 'all'
Requires-Dist: bintensors[numpy] ; extra == 'all'
Requires-Dist: bintensors[quality] ; extra == 'all'
Requires-Dist: bintensors[testing] ; extra == 'all'
Requires-Dist: bintensors[all] ; extra == 'dev'
Provides-Extra: numpy
Provides-Extra: torch
Provides-Extra: jax
Provides-Extra: mlx
Provides-Extra: quality
Provides-Extra: testing
Provides-Extra: all
Provides-Extra: dev
Summary: Another file format for storing your models in a binary encoded format.
Author-email: Luca Vivona <lucavivona01@gmail.com>
Requires-Python: >=3.8
Project-URL: Homepage, https://github.com/GnosisFoundation/bintensors
Project-URL: Source, https://github.com/GnosisFoundation/bintensors
Project-URL: repository, https://github.com/GnosisFoundation/bintensors
